qt3rfsynthcontrol/__init__.py
qt3rfsynthcontrol/device.py
qt3rfsynthcontrol-1.0.1.dist-info/LICENSE
qt3rfsynthcontrol-1.0.1.dist-info/METADATA
qt3rfsynthcontrol-1.0.1.dist-info/WHEEL
qt3rfsynthcontrol-1.0.1.dist-info/top_level.txt
qt3rfsynthcontrol-1.0.1.dist-info/RECORD
