Metadata-Version: 2.1
Name: qt3rfsynthcontrol
Version: 1.0.1
Summary: A package for controlling the Windfreak SynthHD RF generator.
Author-email: "G. Adam Cox" <gadamc@gmail.com>
Maintainer-email: "G. Adam Cox" <gadamc@gmail.com>, Maxwell Parsons <mfpars@uw.edu>
License: BSD 3-Clause License
Project-URL: Homepage, https://github.com/qt3uw/qt3rfsynthcontrol
Project-URL: Source, https://github.com/qt3uw/qt3rfsynthcontrol
Project-URL: Bug Tracker, https://github.com/qt3uw/qt3rfsynthcontrol/issues
Project-URL: Changelog, https://github.com/qt3uw/qt3rfsynthcontrol/releases
Keywords: qt3,microwave,electron spin control,windfreak,synthHD,rf generator,rf synthesizer,rf control,rf
Classifier: Development Status :: 5 - Production/Stable
Classifier: Intended Audience :: Science/Research
Classifier: Topic :: Scientific/Engineering :: Physics
Classifier: Topic :: Scientific/Engineering
Classifier: License :: OSI Approved :: BSD License
Classifier: Programming Language :: Python :: 3.8
Classifier: Programming Language :: Python :: 3.9
Classifier: Programming Language :: Python :: 3.10
Classifier: Programming Language :: Python :: 3.11
Classifier: Programming Language :: Python :: 3 :: Only
Requires-Python: >=3.8
License-File: LICENSE
Requires-Dist: windfreak (==0.3.0)
